zenodio/__init__.py
zenodio/harvest.py
zenodio-0.1.0.dist-info/DESCRIPTION.rst
zenodio-0.1.0.dist-info/METADATA
zenodio-0.1.0.dist-info/RECORD
zenodio-0.1.0.dist-info/WHEEL
zenodio-0.1.0.dist-info/metadata.json
zenodio-0.1.0.dist-info/top_level.txt
